README.md
setup.cfg
setup.py
pacli/__init__.py
pacli/__main__.py
pacli/coin.py
pacli/config.py
pacli/default_conf.py
pacli/export.py
pacli/keystore.py
pacli/provider.py
pacli/tui.py
pacli/utils.py
pacli.egg-info/PKG-INFO
pacli.egg-info/SOURCES.txt
pacli.egg-info/dependency_links.txt
pacli.egg-info/entry_points.txt
pacli.egg-info/requires.txt
pacli.egg-info/top_level.txt