Metadata-Version: 2.1
Name: pacli
Version: 0.4.7.2
Summary: Simple CLI PeerAssets client.
Home-page: https://github.com/peerassets/pacli
Author: Peerchemist
Author-email: peerchemist@protonmail.ch
License: GPL
Keywords: peerassets,blockchain,assets,client
Platform: UNKNOWN
